musica/__init__.py
musica/_musica.cpython-312-aarch64-linux-gnu.so
musica/_version.py
musica/backend.py
musica/constants.py
musica/cuda.py
musica/main.py
musica/carma/__init__.py
musica/carma/carma.py
musica/examples/__init__.py
musica/examples/carma_aluminum.py
musica/examples/carma_sulfate.py
musica/examples/examples.py
musica/examples/lorenz.py
musica/examples/sulfate_box_model.py
musica/examples/ts1_latin_hypercube.py
musica/mechanism_configuration/__init__.py
musica/mechanism_configuration/ancillary.py
musica/mechanism_configuration/arrhenius.py
musica/mechanism_configuration/branched.py
musica/mechanism_configuration/emission.py
musica/mechanism_configuration/first_order_loss.py
musica/mechanism_configuration/mechanism.py
musica/mechanism_configuration/phase.py
musica/mechanism_configuration/phase_species.py
musica/mechanism_configuration/photolysis.py
musica/mechanism_configuration/reaction_component.py
musica/mechanism_configuration/reactions.py
musica/mechanism_configuration/species.py
musica/mechanism_configuration/surface.py
musica/mechanism_configuration/taylor_series.py
musica/mechanism_configuration/ternary_chemical_activation.py
musica/mechanism_configuration/troe.py
musica/mechanism_configuration/tunneling.py
musica/mechanism_configuration/user_defined.py
musica/mechanism_configuration/utils.py
musica/micm/__init__.py
musica/micm/conditions.py
musica/micm/micm.py
musica/micm/solver.py
musica/micm/solver_result.py
musica/micm/state.py
musica/micm/utils.py
musica/tuvx/__init__.py
musica/tuvx/grid.py
musica/tuvx/grid_map.py
musica/tuvx/profile.py
musica/tuvx/profile_map.py
musica/tuvx/radiator.py
musica/tuvx/radiator_map.py
musica/tuvx/tuvx.py
musica-0.14.4.dist-info/licenses/AUTHORS.md
musica-0.14.4.dist-info/licenses/LICENSE
musica.libs/libaec-34bb4966.so.0.0.8
musica.libs/libblas-8ed0a6f9.so.3.8.0
musica.libs/libbrotlicommon-b6e6c8bd.so.1.0.6
musica.libs/libbrotlidec-5094ef0a.so.1.0.6
musica.libs/libcom_err-6d8d18aa.so.2.1
musica.libs/libcrypt-258f54d5.so.1.1.0
musica.libs/libcrypto-3eda328c.so.1.1.1k
musica-0.14.4.dist-info/METADATA
musica-0.14.4.dist-info/WHEEL
musica-0.14.4.dist-info/entry_points.txt
musica-0.14.4.dist-info/RECORD
