Metadata-Version: 2.2
Name: musica
Version: 0.14.4
Summary: MUSICA is a Python library for performing computational simulations in atmospheric chemistry.
Author-Email: Matthew Dawsom <mattdawson@ucar.edu>, Jiwon Gim <jiwongim@ucar.edu>, David Fillmore <fillmore@ucar.edu>, Kyle Shores <kshores@ucar.edu>, Montek Thind <mthind@ucar.edu>
Maintainer-Email: ACOM MUSICA Developers <musica-support@ucar.edu>
License:                                  Apache License
Project-URL: homepage, https://wiki.ucar.edu/display/MUSICA/MUSICA+Home
Requires-Python: >=3.10
Requires-Dist: numpy>=2.0.0
Requires-Dist: pandas>=2.2.0
Requires-Dist: pyyaml>=6.0.2
Requires-Dist: xarray>=2022.3.0
Provides-Extra: test
Requires-Dist: pytest>=7.0.0; extra == "test"
Requires-Dist: pytest-cov>=4.0.0; extra == "test"
Requires-Dist: ussa1976>=0.3.4; platform_machine != "i686" and (platform_machine != "arm64" and platform_system != "Windows") and extra == "test"
Provides-Extra: gpu
Requires-Dist: nvidia-cublas-cu12>=12.6.4.1; extra == "gpu"
Requires-Dist: nvidia-cuda-runtime-cu12>=12.6.68; extra == "gpu"
Provides-Extra: tutorial
Requires-Dist: dask-jobqueue>=0.8.0; extra == "tutorial"
Requires-Dist: dask[distributed]>=2022.3.0; extra == "tutorial"
Requires-Dist: matplotlib>=3.7.0; extra == "tutorial"
Requires-Dist: scipy>=1.10.0; extra == "tutorial"
Requires-Dist: seaborn>=0.12.0; extra == "tutorial"
Requires-Dist: graphviz>=0.18; extra == "tutorial"
